{
  "user": [
    {
      "id": "0c6a",
      "username": "DuroTron",
      "password": "$2a$10$X4wmY6O9/lwTIoBOnlk3pueeWMjWaO1hSAhX9im6I7Z13zHvEQAtW",
      "acquired": [
        {
          "id": 33,
          "type": "armor",
          "materiales": [
            {
              "id": 220,
              "acquired": true
            },
            {
              "id": 221,
              "acquired": true
            },
            {
              "id": 222,
              "acquired": true
            }
          ]
        },
        {
          "id": 1,
          "type": "armor",
          "materiales": [
            {
              "id": 116,
              "acquired": true
            }
          ]
        },
        {
          "id": 2,
          "type": "armor",
          "materiales": [
            {
              "id": 116,
              "acquired": true
            }
          ]
        }
      ],
      "pending": [
        {
          "id": 2,
          "type": "armor",
          "materiales": [
            {
              "id": 116,
              "acquired": false
            }
          ]
        },
        {
          "id": 3,
          "type": "armor",
          "materiales": [
            {
              "id": 116,
              "acquired": false
            }
          ]
        }
      ]
    }
  ]
}